{
  "ignorePaths": [
    "**/node_modules/**",
    "**/vscode-extension/**",
    "**/.git/**",
    ".vscode",
    "megalinter",
    "package-lock.json",
    "report"
  ],
  "language": "en",
  "noConfigSearch": true,
  "words": [
    "AAVE",
    "Autotask",
    "Autotasks",
    "Bignumber",
    "CTOKEN",
    "CTOKENADDRESS",
    "Codespell",
    "forta",
    "IERC",
    "Liquidatable",
    "MULITSIG",
    "Mult",
    "NEWTEST",
    "Offchain",
    "REPORTERADDRESS",
    "UNDERLYINGTOKENADDRESS",
    "USDP",
    "Unitroller",
    "autotask",
    "autotasks",
    "bignumber",
    "calldatas",
    "cbtc",
    "ceth",
    "codespell",
    "collateralized",
    "creds",
    "disctribution",
    "forta",
    "jszip",
    "keyfile",
    "kvstore",
    "liquidatable",
    "nodebuffer",
    "plusplus",
    "proxiable",
    "pyspelling",
    "rojopolis",
    "stablecoins",
    "stefanzweifel",
    "timelock",
    "typoci",
    "unitroller",
    "unobfuscated",
    "volatilities",
    "zipfile"
  ],
  "version": "0.2"
}
